{
	"backtraceGraph" : 
	{
		"commands" : 
		[
			"install"
		],
		"files" : 
		[
			"src/compressor/snappy/CMakeLists.txt"
		],
		"nodes" : 
		[
			{
				"file" : 0
			},
			{
				"command" : 0,
				"file" : 0,
				"line" : 14,
				"parent" : 0
			}
		]
	},
	"installers" : 
	[
		{
			"backtrace" : 1,
			"component" : "Unspecified",
			"destination" : "lib/ceph/compressor",
			"paths" : 
			[
				"lib/libceph_snappy.so.2.0.0",
				"lib/libceph_snappy.so.2"
			],
			"targetId" : "ceph_snappy::@c776f9f7412d0783d96c",
			"targetIndex" : 55,
			"targetInstallNamelink" : "skip",
			"type" : "target"
		},
		{
			"backtrace" : 1,
			"component" : "Unspecified",
			"destination" : "lib/ceph/compressor",
			"paths" : 
			[
				"lib/libceph_snappy.so"
			],
			"targetId" : "ceph_snappy::@c776f9f7412d0783d96c",
			"targetIndex" : 55,
			"targetInstallNamelink" : "only",
			"type" : "target"
		}
	],
	"paths" : 
	{
		"build" : "src/compressor/snappy",
		"source" : "src/compressor/snappy"
	}
}
